rocketprops/InterpProp_scipy.py
rocketprops/PR_eos.py
rocketprops/__init__.py
rocketprops/_prop_template.py
rocketprops/_version.py
rocketprops/colebrook.py
rocketprops/injector_supt.py
rocketprops/line_supt.py
rocketprops/make_scaled_propellant.py
rocketprops/mixing_functions.py
rocketprops/plot_multi_props.py
rocketprops/prop_names.py
rocketprops/rocket_prop.py
rocketprops/scaling_funcs.py
rocketprops/tank_supt.py
rocketprops/unit_conv_data.py
rocketprops/valve_supt.py
rocketprops/examples/Ethane_sg_compare.png
rocketprops/examples/Ethanol_sg_compare.png
rocketprops/examples/F2_sg_compare.png
rocketprops/examples/LOX_sg_compare.png
rocketprops/examples/MMH_valve.py
rocketprops/examples/Methane_sg_compare.png
rocketprops/examples/Methanol_sg_compare.png
rocketprops/examples/N2H4_line.py
rocketprops/examples/N2O4_orifice.py
rocketprops/examples/N2O_sg_compare.png
rocketprops/examples/NH3_sg_compare.png
rocketprops/examples/PH2_sg_compare.png
rocketprops/examples/Propane_CpHvap.png
rocketprops/examples/Propane_SurfSG.png
rocketprops/examples/Propane_TandP.png
rocketprops/examples/Propane_ViscCond.png
rocketprops/examples/Propane_sg_compare.png
rocketprops/examples/Water_sg_compare.png
rocketprops/examples/chk_ambrose_Psat.py
rocketprops/examples/chk_costald_Vm.py
rocketprops/examples/chk_flox.py
rocketprops/examples/chk_m20.py
rocketprops/examples/chk_mhf3_vs_mixture.py
rocketprops/examples/chk_racket_vm.py
rocketprops/examples/compare_comp_liq.py
rocketprops/examples/example_1.py
rocketprops/examples/make_unit_tst_defs.py
rocketprops/examples/make_unit_tst_mix_defs.py
rocketprops/examples/n2h4_mixture_freeze_pts.png
rocketprops/examples/n2h4_tank.py
rocketprops/examples/new_scaled_prop.py
rocketprops/examples/plot_comp_err.py
rocketprops/examples/plot_compressed_liq.py
rocketprops/examples/plot_freeze_pts.py
rocketprops/examples/plot_mon_freeze_pt.py
rocketprops/examples/plot_multi_props.py
rocketprops/props/A50_prop.py
rocketprops/props/CLF5_prop.py
rocketprops-0.1.8.dist-info/AUTHORS.rst
rocketprops-0.1.8.dist-info/LICENSE.txt
rocketprops-0.1.8.dist-info/METADATA
rocketprops-0.1.8.dist-info/WHEEL
rocketprops-0.1.8.dist-info/top_level.txt
rocketprops-0.1.8.dist-info/RECORD
